<?xml version="1.0" encoding="UTF-8"?>
<objects serializationModel="Studio.02.02.00">
	<object class="AudioFile" id="{66255a27-4d7c-48b0-8910-fd4364c80afd}">
		<property name="assetPath">
			<value>spawn_3.wav</value>
		</property>
		<property name="frequencyInKHz">
			<value>44.0999985</value>
		</property>
		<property name="channelCount">
			<value>2</value>
		</property>
		<property name="length">
			<value>0.40999999999999998</value>
		</property>
		<relationship name="masterAssetFolder">
			<destination>{34db274b-8459-40ec-9d66-d6026edbdf2e}</destination>
		</relationship>
	</object>
</objects>
