{"cameraMode":{"drawMode":0,"name":"Shaded","section":"Shading Mode"},"sceneLighting":false,"audioPlay":false,"sceneViewState":{"m_AlwaysRefresh":false,"showFog":true,"showSkybox":false,"showFlares":true,"showImageEffects":true,"showParticleSystems":true,"showVisualEffectGraphs":true,"m_FxEnabled":true},"in2DMode":false,"pivot":{"x":2.895873785018921,"y":0.5337629318237305,"z":3.0112192630767824},"rotation":{"x":0.3987630605697632,"y":-0.3945654630661011,"z":0.19572167098522187,"w":0.804591178894043},"size":5.973544597625732,"orthographic":false}